rearth/__init__.py
rearth/desc.py
rearth/handler.py
rearth-0.0.1.dist-info/LICENSE
rearth-0.0.1.dist-info/METADATA
rearth-0.0.1.dist-info/WHEEL
rearth-0.0.1.dist-info/top_level.txt
rearth-0.0.1.dist-info/RECORD
