Metadata-Version: 2.1
Name: rearth
Version: 0.0.1
Summary: Python package for the RearthServer
Home-page: https://github.com/Nemupy/rearth
Author: Nemupy
Author-email: nemu.otoyume@gmail.com
License-File: LICENSE
